maidenhead/__init__.py
maidenhead-1.1.6.dist-info/LICENSE.txt
maidenhead-1.1.6.dist-info/METADATA
maidenhead-1.1.6.dist-info/RECORD
maidenhead-1.1.6.dist-info/WHEEL
maidenhead-1.1.6.dist-info/top_level.txt
