Metadata-Version: 2.1
Name: maidenhead
Version: 1.1.6
Summary: Maidenhead Locator, Lat Lon coordinate convertor
Home-page: https://github.com/scivision/maidenhead
Author: Michael Hirsch; Henri Kuiper
License: UNKNOWN
Keywords: location,maidenhead
Platform: UNKNOWN
Classifier: Development Status :: 4 - Beta
Classifier: Environment :: Console
Classifier: Programming Language :: Python :: 3.6
Classifier: Programming Language :: Python :: 3.7
Classifier: Topic :: Scientific/Engineering :: GIS
Requires-Python: >=3.6
Provides-Extra: tests
Provides-Extra: tests
Requires-Dist: pytest; extra == 'tests'
Requires-Dist: pytest-cov; extra == 'tests'
Requires-Dist: coveralls; extra == 'tests'
Requires-Dist: flake8; extra == 'tests'
Requires-Dist: mypy; extra == 'tests'
